wikitexthtml/__init__.py
wikitexthtml/enums.py
wikitexthtml/exceptions.py
wikitexthtml/page.py
wikitexthtml/prototype.py
wikitexthtml/render/__init__.py
wikitexthtml/render/bold_and_italic.py
wikitexthtml/render/config.py
wikitexthtml/render/external_link.py
wikitexthtml/render/list_.py
wikitexthtml/render/parameter.py
wikitexthtml/render/parser_function.py
wikitexthtml/render/postprocess.py
wikitexthtml/render/preprocess.py
wikitexthtml/render/section.py
wikitexthtml/render/table.py
wikitexthtml/render/tag.py
wikitexthtml/render/template.py
wikitexthtml/render/wikilink.py
wikitexthtml/render/parser_functions/__init__.py
wikitexthtml/render/parser_functions/exceptions.py
wikitexthtml/render/parser_functions/expr.py
wikitexthtml/render/parser_functions/helpers.py
wikitexthtml/render/parser_functions/if_.py
wikitexthtml/render/parser_functions/ifeq.py
wikitexthtml/render/parser_functions/ifexist.py
wikitexthtml/render/parser_functions/ifexpr.py
wikitexthtml/render/parser_functions/parsetab.py
wikitexthtml/render/parser_functions/string.py
wikitexthtml/render/parser_functions/switch.py
wikitexthtml/render/parser_functions/url.py
wikitexthtml/render/parser_functions/variables.py
wikitexthtml/render/postprocesses/__init__.py
wikitexthtml/render/postprocesses/add_p_blocks.py
wikitexthtml/render/postprocesses/clean_html.py
wikitexthtml/render/postprocesses/fix_dangling_lt.py
wikitexthtml/render/postprocesses/helper.py
wikitexthtml/render/tags/__init__.py
wikitexthtml/render/tags/gallery.py
wikitexthtml/render/wikilinks/__init__.py
wikitexthtml/render/wikilinks/file.py
wikitexthtml/render/wikilinks/internal.py
wikitexthtml-1.2.0.dist-info/LICENSE
wikitexthtml-1.2.0.dist-info/METADATA
wikitexthtml-1.2.0.dist-info/WHEEL
wikitexthtml-1.2.0.dist-info/top_level.txt
wikitexthtml-1.2.0.dist-info/RECORD
