Metadata-Version: 2.1
Name: wikitexthtml
Version: 1.2.0
Summary: Convert wikitext to HTML
Home-page: https://github.com/TrueBrain/wikitexthtml
Author: Patric 'TrueBrain' Stout
Author-email: truebrain@truebrain.nl
License: UNKNOWN
Platform: UNKNOWN
Classifier: Programming Language :: Python :: 3
Classifier: License :: OSI Approved :: GNU Lesser General Public License v3 (LGPLv3)
Classifier: Operating System :: OS Independent
Requires-Python: >=3.8
Requires-Dist: pygments
Requires-Dist: python-slugify
Requires-Dist: ply
Requires-Dist: wikitextparser
